django_pdf_generator/__init__.py
django_pdf_generator/pdf_generator.py
cpppackage3-2.0.0.dist-info/METADATA
cpppackage3-2.0.0.dist-info/WHEEL
cpppackage3-2.0.0.dist-info/top_level.txt
cpppackage3-2.0.0.dist-info/RECORD
