Metadata-Version: 2.1
Name: cpppackage3
Version: 2.0.0
Summary: A short description of my package
Home-page: https://github.com/my_username/my_package
Author: swapnil
Author-email: swapnild333@gmail.com
Classifier: Programming Language :: Python :: 3
Classifier: License :: OSI Approved :: MIT License
Classifier: Operating System :: OS Independent
Requires-Dist: requests (>=2.25.1)
Requires-Dist: numpy (>=1.19.5)
Requires-Dist: bdist-wheel
